task_assembly_bots/__init__.py
task_assembly_bots-0.1.1.dist-info/METADATA
task_assembly_bots-0.1.1.dist-info/WHEEL
task_assembly_bots-0.1.1.dist-info/RECORD
