Metadata-Version: 2.1
Name: task-assembly-bots
Version: 0.1.1
Summary: Library for building Bots for Task Assembly
License: MIT
Author: Dave Schultz
Author-email: dave@taskassembly.com
Requires-Python: >=3.9,<4.0
Classifier: License :: OSI Approved :: MIT License
Classifier: Programming Language :: Python :: 3
Classifier: Programming Language :: Python :: 3.9
Classifier: Programming Language :: Python :: 3.10
Classifier: Programming Language :: Python :: 3.11
Classifier: Programming Language :: Python :: 3.12
